[
  { "part": 1, "sample": "ugknbfddgicrmopn", "expected": "1" },
  { "part": 1, "sample": "aaa", "expected": "1" },
  { "part": 1, "sample": "jchzalrnumimnmhp", "expected": "0" },
  { "part": 1, "sample": "haegwjzuvuyypxyu", "expected": "0" },
  { "part": 1, "sample": "dvszwmarrgswjxmb", "expected": "0" },

  { "part": 2, "sample": "qjhvhtzxzqqjkmpb", "expected": "1" },
  { "part": 2, "sample": "xxyxx", "expected": "1" },
  { "part": 2, "sample": "uurcxstgmygtbstg", "expected": "0" },
  { "part": 2, "sample": "ieodomkazucvgmuy", "expected": "0" }
]
